{
  "dataset_id": "ds004511:sub-S210204:ses-01_cognitive_control_run-01",
  "samples": 253,
  "mnps": {
    "fs_out": 4.0,
    "window_sec": 8.0,
    "overlap": 0.5,
    "window_bounds": true
  },
  "mnps_axes": {
    "names": [
      "m",
      "d",
      "e"
    ],
    "meaning": {
      "m": "mobility",
      "d": "diffusivity",
      "e": "entropy"
    },
    "order": {
      "m": 0,
      "d": 1,
      "e": 2
    }
  },
  "meta_indices": {
    "mean_trace": 0.022397741551076867,
    "mean_rotation_fro": 0.09843813898821038,
    "windows": 251
  },
  "events": [],
  "labels": [],
  "jacobian": {
    "windows": 251,
    "with_centers": true
  },
  "meta_indices_v2": {
    "mean_trace": 0.003238846082240343,
    "mean_rotation_fro": 0.43808968905433715,
    "windows": 251
  },
  "jacobian_9D": {
    "windows": 251,
    "with_centers": true
  },
  "diagnostics": {
    "windows": 251.0,
    "failed": 0.0,
    "j_dot_mode": "gradient",
    "j_dot_dt": 4.0,
    "local_fit_mse_median": 0.0088028060272336,
    "local_fit_mse_baseline_median": 0.00932910293340683,
    "rel_mse_baseline_median": 0.9424122011084438,
    "failed_insufficient_neighbours": 0.0,
    "failed_nonfinite_samples": 0.0,
    "windows_raw": 251.0,
    "hard_invalid_windows": 0.0,
    "hard_invalid_nonfinite_windows": 0.0,
    "hard_invalid_condition_number_windows": 0.0,
    "hard_invalid_condition_number_threshold": 10000000000.0
  },
  "coords_9d": {
    "names": [
      "m_a",
      "m_e",
      "m_o",
      "d_n",
      "d_l",
      "d_s",
      "e_e",
      "e_s",
      "e_m"
    ],
    "export_prefix": "v2_",
    "composites": {
      "m": "m_mean_from_v2",
      "d": "d_mean_from_v2",
      "e": "e_mean_from_v2"
    },
    "groups": {
      "m": [
        "m_a",
        "m_e",
        "m_o"
      ],
      "d": [
        "d_n",
        "d_l",
        "d_s"
      ],
      "e": [
        "e_e",
        "e_s",
        "e_m"
      ]
    }
  },
  "feature_baselines": {
    "eeg_alpha": {
      "abs_median": 0.04348301514983177,
      "abs_mad": 0.014364424630254505,
      "anchor_applied": "local",
      "standardization_center": -1.3616803884506226,
      "standardization_scale": 0.1486548718214035,
      "transformation_applied": "log10 -> robust_z -> clip_6.0"
    },
    "eeg_alpha_theta": {
      "abs_median": 0.9273866415023804,
      "abs_mad": 0.31373540046215054,
      "anchor_applied": "local",
      "standardization_center": 0.9273866415023804,
      "standardization_scale": 0.31373540046215054,
      "transformation_applied": "robust_z -> clip_6.0"
    },
    "eeg_beta": {
      "abs_median": 0.10540979355573654,
      "abs_mad": 0.02850085505694151,
      "anchor_applied": "local",
      "standardization_center": -0.9771190285682678,
      "standardization_scale": 0.12105794087648392,
      "transformation_applied": "log10 -> robust_z -> clip_6.0"
    },
    "eeg_beta_alpha": {
      "abs_median": 2.5846691131591797,
      "abs_mad": 0.6517555416584014,
      "anchor_applied": "local",
      "standardization_center": 2.5846691131591797,
      "standardization_scale": 0.6517555416584014,
      "transformation_applied": "robust_z -> clip_6.0"
    },
    "eeg_delta": {
      "abs_median": 0.07630088925361633,
      "abs_mad": 0.03348202580139041,
      "anchor_applied": "local",
      "standardization_center": -1.117470383644104,
      "standardization_scale": 0.19760434362888335,
      "transformation_applied": "log10 -> robust_z -> clip_6.0"
    },
    "eeg_gamma": {
      "abs_median": 0.05102112889289856,
      "abs_mad": 0.013701214456558227,
      "anchor_applied": "local",
      "standardization_center": -1.2922499179840088,
      "standardization_scale": 0.12134894278049468,
      "transformation_applied": "log10 -> robust_z -> clip_6.0"
    },
    "eeg_sample_entropy": {
      "abs_median": 0.9222977757453918,
      "abs_mad": 0.008390805280208587,
      "anchor_applied": "local",
      "standardization_center": 0.9222977757453918,
      "standardization_scale": 0.008390805280208587,
      "transformation_applied": "robust_z -> clip_6.0"
    },
    "eeg_theta": {
      "abs_median": 0.043655216693878174,
      "abs_mad": 0.012511701093614101,
      "anchor_applied": "local",
      "standardization_center": -1.3599638938903809,
      "standardization_scale": 0.13194784541130064,
      "transformation_applied": "log10 -> robust_z -> clip_6.0"
    },
    "eeg_hjorth_complexity": {
      "abs_median": 1.9288568496704102,
      "abs_mad": 0.08661446771621703,
      "anchor_applied": "local",
      "standardization_center": 1.9288568496704102,
      "standardization_scale": 0.08661446771621703,
      "transformation_applied": "robust_z -> clip_6.0"
    },
    "eeg_hjorth_mobility": {
      "abs_median": 0.7203373312950134,
      "abs_mad": 0.042718602311611176,
      "anchor_applied": "local",
      "standardization_center": 0.7203373312950134,
      "standardization_scale": 0.042718602311611176,
      "transformation_applied": "robust_z -> clip_6.0"
    },
    "eeg_permutation_entropy": {
      "abs_median": 0.9222977757453918,
      "abs_mad": 0.008390805280208587,
      "anchor_applied": "local",
      "standardization_center": 0.9222977757453918,
      "standardization_scale": 0.008390805280208587,
      "transformation_applied": "robust_z -> clip_6.0"
    },
    "embodied_arousal_proxy": {
      "abs_median": 0.08247827738523483,
      "abs_mad": 0.02095046910792589,
      "anchor_applied": "local",
      "standardization_center": 0.08247827738523483,
      "standardization_scale": 0.02095046910792589,
      "transformation_applied": "robust_z -> clip_6.0"
    }
  },
  "subject": "sub-S210204",
  "session": "ses-01",
  "run": "run-01",
  "participant_meta": {
    "participant_id": "sub-S210204",
    "sex": "F",
    "age": 23
  },
  "participant_meta_source": {
    "source_path": "M:\\datasets\\received\\openneuro\\ds004511\\participants.tsv",
    "source_format": "tsv",
    "subject_id_column": "participant_id"
  },
  "participant_mapped_meta": {
    "group": "Healthy",
    "condition": null,
    "task": "cognitive_control"
  },
  "group": "Healthy",
  "task": "cognitive_control",
  "stage_events_path": "M:\\datasets\\received\\openneuro\\ds004511\\sub-S210204\\ses-01\\eeg\\sub-S210204_ses-01_task-CC_run-01_events.tsv",
  "pseudo_stage": {
    "enabled": false
  },
  "coverage": {
    "rule_tag": "default",
    "min_seconds_effective": 60.0,
    "min_epochs_effective": 20,
    "seconds_effective": 1016.0,
    "seconds_measured": 1016.0,
    "seconds_assumed": 1012.0,
    "seconds_method": "timestamps_span"
  },
  "coverage_h5": {
    "status": "available",
    "path": "/coverage",
    "axis_fraction_path": "/coverage/axis_fraction",
    "coordinate_layers_present": [
      "coords_3d_subject_anchored",
      "coords_9d_subject_anchored"
    ],
    "jacobian_layers_present": [
      "jacobian_9D_subject_anchored",
      "jacobian_subject_anchored"
    ]
  },
  "provenance_h5": {
    "status": "available",
    "path": "/provenance",
    "contract_path": "/provenance/contract",
    "anchoring_path": "/provenance/anchoring"
  },
  "jacobian_h5": {
    "primary_path": "/jacobian",
    "primary_v2_path": "/jacobian_9D",
    "layer_paths": [
      "/jacobian_9D_subject_anchored",
      "/jacobian_subject_anchored"
    ]
  },
  "participant_h5": {
    "clinical_json_path": "/participant/clinical_json"
  },
  "created_at": "2026-07-01T20:28:25.015014Z",
  "time_reference": {
    "enabled": false,
    "status": "disabled",
    "source": "wfdb_header",
    "anchor": "first_recording",
    "schema_version": "time_reference.v1"
  },
  "codebooks": {
    "available": [
      "stage"
    ],
    "stage_path": "/codebooks/stage"
  },
  "regional_outputs_h5": {
    "path": "/regional_mnps",
    "available_coordinate_contracts": [
      "subject_anchored"
    ],
    "primary_coordinate_contract": "subject_anchored"
  },
  "coordinate_contracts": {
    "requested_contracts": [
      "subject_anchored"
    ],
    "realized_contracts": [
      "subject_anchored"
    ],
    "skipped_contracts_with_reason": [],
    "available_coordinate_contracts": [
      "subject_anchored"
    ],
    "primary_coordinate_contract": "subject_anchored"
  },
  "jacobian_9D_blocks": {
    "config": {
      "enabled": true,
      "preset": "mde_families_v1",
      "groups": {
        "m": [
          "m_a",
          "m_e",
          "m_o"
        ],
        "d": [
          "d_n",
          "d_l",
          "d_s"
        ],
        "e": [
          "e_e",
          "e_s",
          "e_m"
        ]
      },
      "pairs": "all",
      "include_self": true,
      "include_sym_rot": true,
      "n_blocks": 9
    },
    "rows": [
      {
        "out_group": "m",
        "in_group": "m",
        "out_dim": 3,
        "in_dim": 3,
        "n_timepoints": 251,
        "block_trace_mean": 0.020389512888122484,
        "block_frobenius_mean": 0.20889617502689362,
        "block_anisotropy_mean": 55.567289476375656,
        "c_sym_mean": null,
        "c_rot_mean": null
      },
      {
        "out_group": "m",
        "in_group": "d",
        "out_dim": 3,
        "in_dim": 3,
        "n_timepoints": 251,
        "block_trace_mean": null,
        "block_frobenius_mean": 0.22103869915008545,
        "block_anisotropy_mean": null,
        "c_sym_mean": 0.1394667138913238,
        "c_rot_mean": 0.16946125552948726
      },
      {
        "out_group": "m",
        "in_group": "e",
        "out_dim": 3,
        "in_dim": 3,
        "n_timepoints": 251,
        "block_trace_mean": null,
        "block_frobenius_mean": 0.1495772749185562,
        "block_anisotropy_mean": null,
        "c_sym_mean": 0.13004757688043128,
        "c_rot_mean": 0.13631844677891863
      },
      {
        "out_group": "d",
        "in_group": "m",
        "out_dim": 3,
        "in_dim": 3,
        "n_timepoints": 251,
        "block_trace_mean": null,
        "block_frobenius_mean": 0.213224396109581,
        "block_anisotropy_mean": null,
        "c_sym_mean": 0.1394667138913238,
        "c_rot_mean": 0.16946125552948726
      },
      {
        "out_group": "d",
        "in_group": "d",
        "out_dim": 3,
        "in_dim": 3,
        "n_timepoints": 251,
        "block_trace_mean": 0.033756104080874726,
        "block_frobenius_mean": 0.23188559710979462,
        "block_anisotropy_mean": 72.3523678651369,
        "c_sym_mean": null,
        "c_rot_mean": null
      },
      {
        "out_group": "d",
        "in_group": "e",
        "out_dim": 3,
        "in_dim": 3,
        "n_timepoints": 251,
        "block_trace_mean": null,
        "block_frobenius_mean": 0.15453393757343292,
        "block_anisotropy_mean": null,
        "c_sym_mean": 0.1288821532194358,
        "c_rot_mean": 0.14684969388631236
      },
      {
        "out_group": "e",
        "in_group": "m",
        "out_dim": 3,
        "in_dim": 3,
        "n_timepoints": 251,
        "block_trace_mean": null,
        "block_frobenius_mean": 0.216810941696167,
        "block_anisotropy_mean": null,
        "c_sym_mean": 0.13004757688043128,
        "c_rot_mean": 0.13631844677891863
      },
      {
        "out_group": "e",
        "in_group": "d",
        "out_dim": 3,
        "in_dim": 3,
        "n_timepoints": 251,
        "block_trace_mean": null,
        "block_frobenius_mean": 0.22772762179374695,
        "block_anisotropy_mean": null,
        "c_sym_mean": 0.1288821532194358,
        "c_rot_mean": 0.14684969388631236
      },
      {
        "out_group": "e",
        "in_group": "e",
        "out_dim": 3,
        "in_dim": 3,
        "n_timepoints": 251,
        "block_trace_mean": -0.050906770475824696,
        "block_frobenius_mean": 0.15498319268226624,
        "block_anisotropy_mean": 35.86412048244856,
        "c_sym_mean": null,
        "c_rot_mean": null
      }
    ]
  },
  "ensemble_robustness": {
    "groups_config": {
      "frontal": [
        "Fp1",
        "Fp2",
        "F3",
        "F4",
        "Fz",
        "F7",
        "F8",
        "AF3",
        "AF4",
        "AF7",
        "AF8"
      ],
      "central": [
        "FC1",
        "FC2",
        "C3",
        "Cz",
        "C4",
        "FC3",
        "FC4",
        "FCz"
      ],
      "parietal_occipital": [
        "P3",
        "P4",
        "Pz",
        "O1",
        "O2",
        "PO3",
        "PO4",
        "Oz",
        "P7",
        "P8"
      ],
      "temporal": [
        "T7",
        "T8",
        "TP7",
        "TP8"
      ]
    },
    "groups_realised": [
      "frontal",
      "central",
      "parietal_occipital",
      "temporal"
    ],
    "subcoord_names": [
      "m_a",
      "m_e",
      "m_o",
      "d_n",
      "d_l",
      "d_s",
      "e_e",
      "e_s",
      "e_m"
    ],
    "mean": {
      "m_a": -0.05461684241890907,
      "m_e": 0.0,
      "m_o": 0.0,
      "d_n": 0.0,
      "d_l": 0.0,
      "d_s": 0.0,
      "e_e": 0.0,
      "e_s": 0.0,
      "e_m": 0.0
    },
    "var": {
      "m_a": 0.0009369133040308952,
      "m_e": 0.0,
      "m_o": 0.0,
      "d_n": 0.0,
      "d_l": 0.0,
      "d_s": 0.0,
      "e_e": 0.0,
      "e_s": 0.0,
      "e_m": 0.0
    }
  },
  "robust_summary": {
    "axes": {
      "summary": {
        "m": {
          "point": -0.05064306780695915,
          "ci_low": -0.1385880559682846,
          "ci_high": 0.05849337577819824
        },
        "d": {
          "point": -0.0035984902642667294,
          "ci_low": -0.08515658974647522,
          "ci_high": 0.08874500542879105
        },
        "e": {
          "point": 0.16352306306362152,
          "ci_low": 0.09378902614116669,
          "ci_high": 0.259138286113739
        }
      },
      "reliability": {
        "m": 0.5484155785585333,
        "d": 0.3777244142896675,
        "e": 0.42254144920688275
      }
    },
    "subcoords": {
      "summary": {
        "m_a": {
          "point": 0.033607661724090576,
          "ci_low": -0.1828075796365738,
          "ci_high": 0.1429387778043747
        },
        "m_e": {
          "point": 0.0,
          "ci_low": -0.15497581660747528,
          "ci_high": 0.17220506072044373
        },
        "m_o": {
          "point": 0.0,
          "ci_low": -0.1772187501192093,
          "ci_high": 0.11874771863222122
        },
        "d_n": {
          "point": 0.0,
          "ci_low": -0.09475526213645935,
          "ci_high": 0.11168931424617767
        },
        "d_l": {
          "point": 0.0,
          "ci_low": -0.1733795553445816,
          "ci_high": 0.15938903391361237
        },
        "d_s": {
          "point": 0.0,
          "ci_low": -0.16056956350803375,
          "ci_high": 0.19854258000850677
        },
        "e_e": {
          "point": 0.0,
          "ci_low": -0.17785906791687012,
          "ci_high": 0.16482403874397278
        },
        "e_s": {
          "point": 0.0,
          "ci_low": -0.14677222073078156,
          "ci_high": 0.20149335265159607
        },
        "e_m": {
          "point": 0.0,
          "ci_low": -0.13583402335643768,
          "ci_high": 0.15215593576431274
        }
      },
      "reliability": {
        "m_a": 0.6538269946009159,
        "m_e": 0.647026161281458,
        "m_o": 0.41429499456673524,
        "d_n": 0.7675310967575769,
        "d_l": 0.47816830444693215,
        "d_s": 0.4922692624962814,
        "e_e": 0.6371569415179666,
        "e_s": 0.3247229822901086,
        "e_m": 0.5161267026441233
      }
    }
  },
  "dist_summary": {
    "axes": {
      "m": {
        "n": 253,
        "nan_frac": 0.0,
        "mean": -0.13176011522976946,
        "median": -0.05064306780695915,
        "std": 0.9519925796999626,
        "iqr": 0.970207154750824,
        "mad": 0.4946148581802845,
        "mad_sigma": 0.7333159887380898,
        "skewness": -0.9701083882161634,
        "kurtosis_excess": 1.9761772914121725,
        "delta_mean_median": -0.08111704742281031
      },
      "d": {
        "n": 253,
        "nan_frac": 0.0,
        "mean": 0.03568724517088398,
        "median": -0.0035984902642667294,
        "std": 0.6865994575027992,
        "iqr": 0.6960253119468689,
        "mad": 0.35685651609674096,
        "mad_sigma": 0.5290754707650281,
        "skewness": 0.41340263448870224,
        "kurtosis_excess": 2.945031847816743,
        "delta_mean_median": 0.03928573543515071
      },
      "e": {
        "n": 253,
        "nan_frac": 0.0,
        "mean": 0.045944680623607084,
        "median": 0.16352306306362152,
        "std": 0.8564672765009831,
        "iqr": 0.8780892491340637,
        "mad": 0.41808725893497467,
        "mad_sigma": 0.6198561700969935,
        "skewness": -1.1326837272747234,
        "kurtosis_excess": 4.068467379948971,
        "delta_mean_median": -0.11757838244001444
      }
    },
    "subcoords": {
      "m_a": {
        "n": 253,
        "nan_frac": 0.0,
        "mean": -0.32630702860565053,
        "median": 0.033607661724090576,
        "std": 1.359109683821269,
        "iqr": 1.3315520286560059,
        "mad": 0.6320783495903015,
        "mad_sigma": 0.937119361102581,
        "skewness": -1.620717604684866,
        "kurtosis_excess": 3.1773936364694864,
        "delta_mean_median": -0.3599146903297411
      },
      "m_e": {
        "n": 253,
        "nan_frac": 0.0,
        "mean": -0.14638394409267916,
        "median": 0.0,
        "std": 1.3355106848541698,
        "iqr": 1.3328419923782349,
        "mad": 0.674490749835968,
        "mad_sigma": 0.9999999857068061,
        "skewness": -1.2580221997844017,
        "kurtosis_excess": 3.0108773306634324,
        "delta_mean_median": -0.14638394409267916
      },
      "m_o": {
        "n": 253,
        "nan_frac": 0.0,
        "mean": 0.15415588150367673,
        "median": 0.0,
        "std": 1.086167533488972,
        "iqr": 1.3439534306526184,
        "mad": 0.674490749835968,
        "mad_sigma": 0.9999999857068061,
        "skewness": 1.0245015554326589,
        "kurtosis_excess": 1.6889554546513699,
        "delta_mean_median": 0.15415588150367673
      },
      "d_n": {
        "n": 253,
        "nan_frac": 0.0,
        "mean": 0.5526073548626228,
        "median": 0.0,
        "std": 1.8296607516619696,
        "iqr": 1.4624695181846619,
        "mad": 0.674490749835968,
        "mad_sigma": 0.9999999857068061,
        "skewness": 1.6636197599450009,
        "kurtosis_excess": 2.159833629820106,
        "delta_mean_median": 0.5526073548626228
      },
      "d_l": {
        "n": 253,
        "nan_frac": 0.0,
        "mean": -0.3241208761400385,
        "median": 0.0,
        "std": 1.4345235948166308,
        "iqr": 1.4593219757080078,
        "mad": 0.674490749835968,
        "mad_sigma": 0.9999999857068061,
        "skewness": -1.6719119634262407,
        "kurtosis_excess": 3.637355577639405,
        "delta_mean_median": -0.3241208761400385
      },
      "d_s": {
        "n": 253,
        "nan_frac": 0.0,
        "mean": 0.16633937674254295,
        "median": 0.0,
        "std": 1.035356448570841,
        "iqr": 1.3301752805709839,
        "mad": 0.674490749835968,
        "mad_sigma": 0.9999999857068061,
        "skewness": 1.2106459302105352,
        "kurtosis_excess": 3.4572724194314954,
        "delta_mean_median": 0.16633937674254295
      },
      "e_e": {
        "n": 253,
        "nan_frac": 0.0,
        "mean": -0.13544124240063043,
        "median": 0.0,
        "std": 1.097188603339572,
        "iqr": 1.3688215613365173,
        "mad": 0.6744906306266785,
        "mad_sigma": 0.9999998089671135,
        "skewness": -0.9666702235088495,
        "kurtosis_excess": 1.6541119657576457,
        "delta_mean_median": -0.13544124240063043
      },
      "e_s": {
        "n": 253,
        "nan_frac": 0.0,
        "mean": 0.29774207876730163,
        "median": 0.0,
        "std": 1.6793874596942742,
        "iqr": 1.3559443354606628,
        "mad": 0.674490749835968,
        "mad_sigma": 0.9999999857068061,
        "skewness": 1.1242820775584195,
        "kurtosis_excess": 3.9960884516335096,
        "delta_mean_median": 0.29774207876730163
      },
      "e_m": {
        "n": 253,
        "nan_frac": 0.0,
        "mean": -0.018599989927068294,
        "median": 0.0,
        "std": 0.9426572857350237,
        "iqr": 1.3342741131782532,
        "mad": 0.674490749835968,
        "mad_sigma": 0.9999999857068061,
        "skewness": -0.0012051345496631157,
        "kurtosis_excess": -0.31569982653448925,
        "delta_mean_median": -0.018599989927068294
      }
    }
  },
  "conventional_eeg": {
    "schema_version": "mndm.conventional_eeg.v1",
    "packs": [
      "complexity",
      "tier1"
    ],
    "column_count": 16,
    "columns": [
      "eeg_conventional_complexity_hjorth_complexity",
      "eeg_conventional_complexity_permutation_entropy",
      "eeg_conventional_complexity_spectral_entropy",
      "eeg_conventional_peak_alpha_frequency",
      "eeg_conventional_peak_median_frequency",
      "eeg_conventional_peak_spectral_edge_95",
      "eeg_conventional_ratio_alpha_theta",
      "eeg_conventional_ratio_beta_alpha",
      "eeg_conventional_ratio_delta_alpha",
      "eeg_conventional_ratio_slowing_index",
      "eeg_conventional_ratio_theta_alpha",
      "eeg_conventional_relative_alpha",
      "eeg_conventional_relative_beta",
      "eeg_conventional_relative_delta",
      "eeg_conventional_relative_gamma",
      "eeg_conventional_relative_theta"
    ],
    "families": {
      "complexity": {
        "hjorth_complexity": {
          "column": "eeg_conventional_complexity_hjorth_complexity",
          "n": 253,
          "nan_frac": 0.0,
          "mean": 1.9610405527930033,
          "median": 1.928856883797007,
          "std": 0.17362890130890055,
          "iqr": 0.11744445928871916,
          "mad": 0.05842068510092169,
          "mad_sigma": 0.08661450773062648,
          "skewness": 2.4733330227884234,
          "kurtosis_excess": 11.596728629807924,
          "delta_mean_median": 0.03218366899599623
        },
        "permutation_entropy": {
          "column": "eeg_conventional_complexity_permutation_entropy",
          "n": 253,
          "nan_frac": 0.0,
          "mean": 0.9211613159150762,
          "median": 0.9222977967869852,
          "std": 0.009206296032112201,
          "iqr": 0.011485533929049607,
          "mad": 0.00565948221424617,
          "mad_sigma": 0.008390748330841372,
          "skewness": -0.9666709563196464,
          "kurtosis_excess": 1.6541153683085685,
          "delta_mean_median": -0.0011364808719089847
        },
        "spectral_entropy": {
          "column": "eeg_conventional_complexity_spectral_entropy",
          "n": 253,
          "nan_frac": 0.0,
          "mean": 4.014898984951141,
          "median": 4.0705442315867355,
          "std": 0.22586963551160438,
          "iqr": 0.16079965162991616,
          "mad": 0.06977811005667967,
          "mad_sigma": 0.10345302597003327,
          "skewness": -3.2426513255031257,
          "kurtosis_excess": 12.60396000311996,
          "delta_mean_median": -0.05564524663559478
        }
      },
      "peak": {
        "alpha_frequency": {
          "column": "eeg_conventional_peak_alpha_frequency",
          "n": 253,
          "nan_frac": 0.0,
          "mean": 10.3300395256917,
          "median": 10.5,
          "std": 1.0922231373839912,
          "iqr": 1.5,
          "mad": 0.75,
          "mad_sigma": 1.11195,
          "skewness": -0.5534376272405093,
          "kurtosis_excess": -0.6125869821894003,
          "delta_mean_median": -0.16996047430830075
        },
        "median_frequency": {
          "column": "eeg_conventional_peak_median_frequency",
          "n": 253,
          "nan_frac": 0.0,
          "mean": 11.113235775459309,
          "median": 11.320368666667578,
          "std": 3.333064256961793,
          "iqr": 2.4950222507535305,
          "mad": 1.2697187200949642,
          "mad_sigma": 1.8824849744127938,
          "skewness": 0.16406045648413817,
          "kurtosis_excess": 6.757434518667942,
          "delta_mean_median": -0.2071328912082695
        },
        "spectral_edge_95": {
          "column": "eeg_conventional_peak_spectral_edge_95",
          "n": 253,
          "nan_frac": 0.0,
          "mean": 42.554005514423025,
          "median": 42.64812129162836,
          "std": 1.4201419819685162,
          "iqr": 1.735542598587017,
          "mad": 0.8824612446915125,
          "mad_sigma": 1.3083370413796365,
          "skewness": -0.26062362082170587,
          "kurtosis_excess": 1.1328504243371045,
          "delta_mean_median": -0.0941157772053316
        }
      },
      "ratio": {
        "alpha_theta": {
          "column": "eeg_conventional_ratio_alpha_theta",
          "n": 253,
          "nan_frac": 0.0,
          "mean": 0.9795731906738729,
          "median": 0.9273866659948017,
          "std": 0.3248279664110859,
          "iqr": 0.41732303162794226,
          "mad": 0.2116116230829751,
          "mad_sigma": 0.3137353923828189,
          "skewness": 1.2106459468685564,
          "kurtosis_excess": 3.457272613368345,
          "delta_mean_median": 0.052186524679071256
        },
        "beta_alpha": {
          "column": "eeg_conventional_ratio_beta_alpha",
          "n": 253,
          "nan_frac": 0.0,
          "mean": 2.6851410715586446,
          "median": 2.584669013164339,
          "std": 0.7079157452333766,
          "iqr": 0.8759292227085678,
          "mad": 0.4396033008618314,
          "mad_sigma": 0.6517558538577513,
          "skewness": 1.0245015449074393,
          "kurtosis_excess": 1.688955413936288,
          "delta_mean_median": 0.10047205839430573
        },
        "delta_alpha": {
          "column": "eeg_conventional_ratio_delta_alpha",
          "n": 253,
          "nan_frac": 0.0,
          "mean": 2.2499618981802407,
          "median": 1.8448264347248038,
          "std": 1.8706043327367716,
          "iqr": 0.9830100187658442,
          "mad": 0.49332127964400674,
          "mad_sigma": 0.7313981292002043,
          "skewness": 4.261151299578634,
          "kurtosis_excess": 22.171558790618068,
          "delta_mean_median": 0.40513546345543694
        },
        "slowing_index": {
          "column": "eeg_conventional_ratio_slowing_index",
          "n": 253,
          "nan_frac": 0.0,
          "mean": 0.9056267682951474,
          "median": 0.8171166160764871,
          "std": 0.49695183042306196,
          "iqr": 0.2788532986087464,
          "mad": 0.14437717312589315,
          "mad_sigma": 0.21405359687644918,
          "skewness": 5.598665096837028,
          "kurtosis_excess": 42.019620925302036,
          "delta_mean_median": 0.08851015221866032
        },
        "theta_alpha": {
          "column": "eeg_conventional_ratio_theta_alpha",
          "n": 253,
          "nan_frac": 0.0,
          "mean": 1.1306976668076392,
          "median": 1.0782988764749022,
          "std": 0.36667809936582846,
          "iqr": 0.47297735332195867,
          "mad": 0.24752949415671166,
          "mad_sigma": 0.36698722803674066,
          "skewness": 0.8512784403184803,
          "kurtosis_excess": 0.8969896259484997,
          "delta_mean_median": 0.05239879033273698
        }
      },
      "relative": {
        "alpha": {
          "column": "eeg_conventional_relative_alpha",
          "n": 253,
          "nan_frac": 0.0,
          "mean": 0.12763329264192108,
          "median": 0.12926356762877705,
          "std": 0.03270038182596567,
          "iqr": 0.04492294452389868,
          "mad": 0.02268226339320517,
          "mad_sigma": 0.033628723706765985,
          "skewness": 0.028646861181837797,
          "kurtosis_excess": 0.23578841833457131,
          "delta_mean_median": -0.001630274986855973
        },
        "beta": {
          "column": "eeg_conventional_relative_beta",
          "n": 253,
          "nan_frac": 0.0,
          "mean": 0.3241051206829019,
          "median": 0.3240164735683017,
          "std": 0.048723102533259566,
          "iqr": 0.057753965737546764,
          "mad": 0.028720916678394548,
          "mad_sigma": 0.04258163106738776,
          "skewness": -0.7997299788399752,
          "kurtosis_excess": 2.9322983130871734,
          "delta_mean_median": 8.864711460021546e-05
        },
        "delta": {
          "column": "eeg_conventional_relative_delta",
          "n": 253,
          "nan_frac": 0.0,
          "mean": 0.24588800149467446,
          "median": 0.2348321265230012,
          "std": 0.08442569279479008,
          "iqr": 0.07976228321625614,
          "mad": 0.04014112723383459,
          "mad_sigma": 0.05951323523688316,
          "skewness": 2.1467262882510547,
          "kurtosis_excess": 7.578319706228466,
          "delta_mean_median": 0.011055874971673263
        },
        "gamma": {
          "column": "eeg_conventional_relative_gamma",
          "n": 253,
          "nan_frac": 0.0,
          "mean": 0.1670398151783192,
          "median": 0.16099585206044026,
          "std": 0.04069569733141471,
          "iqr": 0.028686089257168756,
          "mad": 0.014482612401050698,
          "mad_sigma": 0.021471921145797764,
          "skewness": 3.3095697572147285,
          "kurtosis_excess": 18.134698870063897,
          "delta_mean_median": 0.006043963117878942
        },
        "theta": {
          "column": "eeg_conventional_relative_theta",
          "n": 253,
          "nan_frac": 0.0,
          "mean": 0.1353337700021834,
          "median": 0.1351400220574103,
          "std": 0.027998256747853473,
          "iqr": 0.03883811434163903,
          "mad": 0.019275815763861143,
          "mad_sigma": 0.02857832445150053,
          "skewness": -0.15174227247846875,
          "kurtosis_excess": -0.186886547709455,
          "delta_mean_median": 0.00019374794477311497
        }
      }
    }
  },
  "tau_summary": {
    "axes": {
      "m": {
        "tau_sec": 8.0,
        "dt_sec": 4.0,
        "max_lag_sec": 60.0,
        "threshold": 0.36787944117144233,
        "nan_frac": 0.0,
        "nan_policy": "strict"
      },
      "d": {
        "tau_sec": 8.0,
        "dt_sec": 4.0,
        "max_lag_sec": 60.0,
        "threshold": 0.36787944117144233,
        "nan_frac": 0.0,
        "nan_policy": "strict"
      },
      "e": {
        "tau_sec": 8.0,
        "dt_sec": 4.0,
        "max_lag_sec": 60.0,
        "threshold": 0.36787944117144233,
        "nan_frac": 0.0,
        "nan_policy": "strict"
      }
    },
    "subcoords": {
      "m_a": {
        "tau_sec": 12.0,
        "dt_sec": 4.0,
        "max_lag_sec": 60.0,
        "threshold": 0.36787944117144233,
        "nan_frac": 0.0,
        "nan_policy": "strict"
      },
      "m_e": {
        "tau_sec": 8.0,
        "dt_sec": 4.0,
        "max_lag_sec": 60.0,
        "threshold": 0.36787944117144233,
        "nan_frac": 0.0,
        "nan_policy": "strict"
      },
      "m_o": {
        "tau_sec": 8.0,
        "dt_sec": 4.0,
        "max_lag_sec": 60.0,
        "threshold": 0.36787944117144233,
        "nan_frac": 0.0,
        "nan_policy": "strict"
      },
      "d_n": {
        "tau_sec": 12.0,
        "dt_sec": 4.0,
        "max_lag_sec": 60.0,
        "threshold": 0.36787944117144233,
        "nan_frac": 0.0,
        "nan_policy": "strict"
      },
      "d_l": {
        "tau_sec": 8.0,
        "dt_sec": 4.0,
        "max_lag_sec": 60.0,
        "threshold": 0.36787944117144233,
        "nan_frac": 0.0,
        "nan_policy": "strict"
      },
      "d_s": {
        "tau_sec": 8.0,
        "dt_sec": 4.0,
        "max_lag_sec": 60.0,
        "threshold": 0.36787944117144233,
        "nan_frac": 0.0,
        "nan_policy": "strict"
      },
      "e_e": {
        "tau_sec": 8.0,
        "dt_sec": 4.0,
        "max_lag_sec": 60.0,
        "threshold": 0.36787944117144233,
        "nan_frac": 0.0,
        "nan_policy": "strict"
      },
      "e_s": {
        "tau_sec": 8.0,
        "dt_sec": 4.0,
        "max_lag_sec": 60.0,
        "threshold": 0.36787944117144233,
        "nan_frac": 0.0,
        "nan_policy": "strict"
      },
      "e_m": {
        "tau_sec": 8.0,
        "dt_sec": 4.0,
        "max_lag_sec": 60.0,
        "threshold": 0.36787944117144233,
        "nan_frac": 0.0,
        "nan_policy": "strict"
      }
    }
  },
  "tier2_jacobian": {
    "signed_divergence_balance": {
      "n": 251,
      "frac_pos": 0.5219123505976095,
      "frac_neg": 0.47808764940239046,
      "mean_pos": 0.0803747085387528,
      "mean_neg": -0.04089378083469152,
      "mean_abs": 0.06149936461649242
    },
    "jacobian_condition_number": {
      "n": 251,
      "nan_frac": 0.0,
      "mean": 57.61968144566343,
      "median": 12.352798920710482,
      "std": 321.04830753153874,
      "iqr": 23.32058294455552,
      "mad": 7.6206684903873185,
      "mad_sigma": 11.298403103848237,
      "skewness": 12.718098806927761,
      "kurtosis_excess": 174.58484173702848,
      "delta_mean_median": 45.26688252495295,
      "estimated_on_windows": 251,
      "total_finite_windows": 251,
      "subsampled": false
    },
    "rotation_coherence": {
      "n": 251,
      "mean_resultant_length": 0.28694967960324974,
      "mean_axis": [
        0.7052101094967281,
        0.6767211166164467,
        -0.21148813628428945
      ]
    },
    "rel_mse_baseline": {
      "n": 251,
      "nan_frac": 0.0,
      "mean": 0.9433937949013425,
      "median": 0.9424121975898743,
      "std": 0.06155768483047137,
      "iqr": 0.060619890689849854,
      "mad": 0.030768990516662598,
      "mad_sigma": 0.04561810534000396,
      "skewness": 0.9221953752674392,
      "kurtosis_excess": 5.283081844887331,
      "delta_mean_median": 0.0009815973114681853,
      "note": "Relative local-fit MSE vs intercept-only baseline (<1 better than baseline)."
    }
  },
  "tier2_emmi": {
    "speed_mean": 0.1572140051957376,
    "speed_median": 0.13022064889728127,
    "mv_median": 2.98002118656603e-05,
    "mv_abs_median": 2.98002118656603e-05,
    "emmi_e_over_m_median": -3.2289328064985607,
    "mv_over_speed_median": 0.0002288439822563537
  },
  "entropy_qc": {
    "e_e": {
      "var": 1.2038228312982404,
      "n_unique": 253,
      "nan_frac": 0.0,
      "provisional": false
    },
    "e_s": {
      "var": 2.8203422397783875,
      "n_unique": 247,
      "nan_frac": 0.0,
      "provisional": false
    },
    "e_m": {
      "var": 0.8886027583493221,
      "n_unique": 250,
      "nan_frac": 0.0,
      "provisional": false
    }
  },
  "extensions": {
    "regional_data_available": false,
    "rfm": {
      "status": "skipped_no_regional_bold"
    },
    "o_koh": {
      "status": "skipped_no_regional_bold"
    },
    "tig": {
      "status": "skipped_no_regional_bold"
    }
  },
  "ndt_ingest": {
    "mapping_source": "mnps_projection",
    "normalize_mode_effective": "robust_z"
  },
  "mnps_3d": {
    "mode_requested": "from_v2",
    "mode_effective": "from_v2",
    "x_definition": "derived_mde_from_v2_fixed_weighted_projection",
    "from_v2": {
      "aggregation_requested": "fixed_weighted_projection",
      "aggregation": "fixed_weighted_projection",
      "legacy_pooling": "mean",
      "map": {
        "m": [
          "m_a",
          "m_e",
          "m_o"
        ],
        "d": [
          "d_n",
          "d_l",
          "d_s"
        ],
        "e": [
          "e_e",
          "e_s",
          "e_m"
        ]
      },
      "v1_mapping_source": "mnps_projection.v1_mapping",
      "v1_mapping_input": {
        "m": {
          "m_a": 0.62,
          "m_e": 0.55,
          "m_o": 0.45
        },
        "d": {
          "d_n": 0.5,
          "d_l": 0.82,
          "d_s": 0.28
        },
        "e": {
          "e_e": 0.85,
          "e_s": 0.62,
          "e_m": 0.03
        }
      },
      "v1_mapping_normalized": {
        "m": {
          "m_a": 0.6574203372001648,
          "m_e": 0.5831954479217529,
          "m_o": 0.47715988755226135
        },
        "d": {
          "d_n": 0.4998001158237457,
          "d_l": 0.819672167301178,
          "d_s": 0.2798880636692047
        },
        "e": {
          "e_e": 0.8075850605964661,
          "e_s": 0.5890620350837708,
          "e_m": 0.028503000736236572
        }
      },
      "v1_mapping_matrix": [
        [
          0.6574203372001648,
          0.0,
          0.0
        ],
        [
          0.5831954479217529,
          0.0,
          0.0
        ],
        [
          0.47715988755226135,
          0.0,
          0.0
        ],
        [
          0.0,
          0.4998001158237457,
          0.0
        ],
        [
          0.0,
          0.819672167301178,
          0.0
        ],
        [
          0.0,
          0.2798880636692047,
          0.0
        ],
        [
          0.0,
          0.0,
          0.8075850605964661
        ],
        [
          0.0,
          0.0,
          0.5890620350837708
        ],
        [
          0.0,
          0.0,
          0.028503000736236572
        ]
      ],
      "v1_mapping_matrix_rows": [
        "m_a",
        "m_e",
        "m_o",
        "d_n",
        "d_l",
        "d_s",
        "e_e",
        "e_s",
        "e_m"
      ],
      "v1_mapping_hash": "fc17689f4f8408dd321e4a6a293426ca4240892b93647558f136a277b7a7be7b",
      "fallback_reason": null
    }
  },
  "geometry_contract": {
    "policy_version": "standard_invalidity_v1",
    "status": "ok",
    "primary_requires_coords_9d": true,
    "shared_time_grid": {
      "epochs_before_policy": 253,
      "epochs_retained": 253,
      "epochs_dropped": 0,
      "drop_fraction": 0.0,
      "dropped_epoch_indices_preview": [],
      "drop_reason_counts": {
        "mnps_3d_nonfinite_rows": 0,
        "coords_9d_nonfinite_rows_affecting_primary": 0
      }
    },
    "mnps_3d": {
      "finite_row_fraction_before": 1.0,
      "nonfinite_row_count": 0,
      "degenerate_axes": [],
      "all_nan_axes": []
    },
    "coords_9d": {
      "available": true,
      "shape_matches_time_grid": true,
      "finite_row_fraction_before": 1.0,
      "nonfinite_row_count": 0,
      "nonfinite_rows_retained_on_shared_grid": 0,
      "degenerate_axes": [],
      "all_nan_axes": []
    },
    "time_grid": {
      "status": "ok",
      "warnings": [],
      "window_count": 253,
      "finite_window_bounds_fraction": 1.0,
      "dt_source": "window_start",
      "dt_sec_runtime": 4.0,
      "dt_sec_config": 4.0,
      "window_sec_config": 8.0,
      "dt_matches_runtime": true,
      "dt_matches_config_formula": true,
      "window_len_matches_config": true,
      "nonpositive_dt_count": 0,
      "nonpositive_window_len_count": 0,
      "dt_intervals_sec": {
        "n": 252,
        "mean": 4.0,
        "median": 4.0,
        "iqr": 0.0,
        "p95": 4.0,
        "max": 4.0
      },
      "window_lengths_sec": {
        "n": 253,
        "mean": 8.0,
        "median": 8.0,
        "iqr": 0.0,
        "p95": 8.0,
        "max": 8.0
      }
    },
    "jacobian": {
      "policy_version": "standard_invalidity_v1",
      "status": "ok",
      "windows_raw": 251,
      "windows_retained": 251,
      "invalid_windows": 0,
      "invalid_window_fraction": 0.0,
      "condition_number_threshold": 10000000000.0,
      "invalid_reason_counts": {
        "nonfinite_windows": 0,
        "condition_number_windows": 0
      },
      "invalid_centers_preview": []
    },
    "jacobian_9d": {
      "policy_version": "standard_invalidity_v1",
      "status": "ok",
      "windows_raw": 251,
      "windows_retained": 251,
      "invalid_windows": 0,
      "invalid_window_fraction": 0.0,
      "condition_number_threshold": 10000000000.0,
      "invalid_reason_counts": {
        "nonfinite_windows": 0,
        "condition_number_windows": 0
      },
      "invalid_centers_preview": []
    }
  },
  "provenance": {
    "mnps_9d_definition_version": "2.0",
    "mnps_9d_constructs": {
      "e_e": {
        "intended_metric": "permutation_entropy",
        "actual_metric_used": "permutation_entropy",
        "metric_backend": "numpy",
        "params": {
          "order": 5,
          "delay": 1,
          "normalize": true
        },
        "degraded_mode": false,
        "reason": null
      }
    },
    "reproducibility": {
      "seed": 42,
      "seed_source": "robustness.seed",
      "stochastic_components": [
        "feature_worker_rng",
        "robustness_bootstrap",
        "null_sanity_tests",
        "epoch_stage_stratified_sampling",
        "preprocess_ica",
        "fmri_louvain_modularity"
      ],
      "deterministic_outputs": [
        "mnps_3d",
        "mnps_3d_dot",
        "coords_9d",
        "nn_indices",
        "jacobian.J_hat",
        "jacobian.J_dot",
        "jacobian_9D.J_hat",
        "jacobian_9D.J_dot"
      ],
      "nn_indices_hash_saved": "6c7cc6cf1d0e009cd7c860748f432f06c40906b8030a2e3da848d0b2b0c1bd9c",
      "x_hash_saved": "98e8904e796b3c7a282340d115cb618c048d0937d67b0961a4032b030c4335ad",
      "x_hash_knn_input": "98e8904e796b3c7a282340d115cb618c048d0937d67b0961a4032b030c4335ad",
      "x_hash_jacobian_input": "98e8904e796b3c7a282340d115cb618c048d0937d67b0961a4032b030c4335ad",
      "jacobian_hash_saved": "f118cee874de66231ed01e9bfe13584f4b4e2133e80ad14a925b9f73f40bdb40",
      "jacobian_dot_hash_saved": "9490de026ecca213ea0eee4f2e01f27cfc25a3b1cf2112a57a7329b4803ed6a3",
      "coords_9d_hash_saved": "db8df7cc824e1370ec062d225a89f46781596d6e07f1b146d95d759bc87496f6",
      "coords_9d_hash_knn_input": "db8df7cc824e1370ec062d225a89f46781596d6e07f1b146d95d759bc87496f6",
      "coords_9d_hash_jacobian_input": "db8df7cc824e1370ec062d225a89f46781596d6e07f1b146d95d759bc87496f6",
      "jacobian_9d_hash_saved": "71b19d89d6bc4f85d84582cb851b6b7379fd0e8cdd045932893da7c388dc8c73",
      "jacobian_9d_dot_hash_saved": "727775531846bc38d8369078ae4a9723c160208b3be6f1070c12d224857065c8"
    }
  },
  "feature_exports": {
    "raw_h5_path": "/features_raw",
    "robust_z_h5_path": "/features_robust_z",
    "scope": "all_numeric_feature_columns_excluding_metadata",
    "column_count": 139,
    "names_hash": "4666879c6733a6859b50e03e4321ec417d6347299ba37fdb4d9df680ce1328f6",
    "metadata_fields": [
      "backend",
      "degraded_mode",
      "fallback_reason",
      "feature_name",
      "group_label",
      "is_regional",
      "projection_normalize_mode",
      "projection_transform_applied",
      "projection_transform_steps",
      "raw_abs_mad",
      "raw_abs_median",
      "robust_z_center",
      "robust_z_scale",
      "source_column",
      "used_anywhere",
      "used_by_coords_9d",
      "used_by_mnps_3d",
      "used_by_regional_projection"
    ]
  },
  "anchor_hrv_v0_1": {
    "enabled": true,
    "source": "ecg",
    "window_sec": 60.0,
    "window_mode": "centered",
    "min_nn_intervals": 20,
    "min_coverage_fraction": 0.5,
    "max_artifact_fraction": 0.25,
    "feature_names": [
      "ecg_hrv_hr_mean_bpm",
      "ecg_hrv_ibi_mean_ms",
      "ecg_hrv_sdnn_ms",
      "ecg_hrv_rmssd_ms",
      "ecg_hrv_pnn50",
      "ecg_hrv_nn_count",
      "ecg_hrv_artifact_fraction",
      "ecg_hrv_coverage_fraction",
      "ecg_hrv_quality_score",
      "ecg_hrv_dominant_stage_frac",
      "ecg_hrv_n_stage_labels",
      "ecg_hrv_contains_excluded_label"
    ],
    "quality_feature_names": [
      "ecg_hrv_nn_count",
      "ecg_hrv_artifact_fraction",
      "ecg_hrv_coverage_fraction",
      "ecg_hrv_quality_score"
    ],
    "features_h5_path": "/features_raw"
  },
  "_TENTATIVE_NOTE": "Metrics such as baseline_comparisons, mnps_mnj_sanity, null_sanity_tests, tier2_jacobian, tier2_emmi, tau_summary, and dist_summary are provided as tentative QA summaries only. Real statistical verification and interpretation must be performed downstream in the analysis repository."
}